cn2vn/__init__.py
cn2vn/converter.py
cn2vn/dictionary.json
cn2vn-0.2.1.dist-info/METADATA
cn2vn-0.2.1.dist-info/WHEEL
cn2vn-0.2.1.dist-info/top_level.txt
cn2vn-0.2.1.dist-info/RECORD
