Metadata-Version: 2.4
Name: cn2vn
Version: 0.2.1
Summary: A library to convert Chinese text to Vietnamese using Sino-Vietnamese readings
Home-page: https://github.com/jetaudio.media/cn2vn
Author: jetaudio.media
Author-email: jetaudio.media@gmail.com
Classifier: Programming Language :: Python :: 3
Classifier: License :: OSI Approved :: MIT License
Classifier: Operating System :: OS Independent
Requires-Python: >=3.6
Dynamic: author
Dynamic: author-email
Dynamic: classifier
Dynamic: description
Dynamic: description-content-type
Dynamic: home-page
Dynamic: requires-python
Dynamic: summary
